COPYING
INSTALL
MANIFEST.in
README
exiassign
exiconvert
exigate
exigui
exiimport
exiperson
exirename
setup.py
debian/changelog
debian/compat
debian/control
debian/copyright
debian/dirs
debian/exiflow.preinst
debian/rules
debian/source/format
exiflow/__init__.py
exiflow/configfile.py
exiflow/exiassign.py
exiflow/exiconvert.py
exiflow/exif.py
exiflow/exigate.py
exiflow/exigui.glade
exiflow/exigui.py
exiflow/exiimport.py
exiflow/exiperson.py
exiflow/exirename.py
exiflow/filelist.py
exiflow/gthumb.py
tests/NikonD70.py
tests/test_exif.py
tests/test_exiimport.py
tests/test_exirename.py
tests/testdata/NikonD70.jpg
tests/testdata/NikonD70_ImageDescription_2rows_latin1.jpg
tests/testdata/NikonD70_ImageDescription_2rows_utf8.jpg
tests/testdata/NikonD70_two_keywords_incl_space.jpg
tests/testdata/python.jpg